LICENSE
README.md
setup.py
googlesearch/__init__.py
googlesearch/user_agents.py
warpspeed_googlesearch_python.egg-info/PKG-INFO
warpspeed_googlesearch_python.egg-info/SOURCES.txt
warpspeed_googlesearch_python.egg-info/dependency_links.txt
warpspeed_googlesearch_python.egg-info/requires.txt
warpspeed_googlesearch_python.egg-info/top_level.txt