Metadata-Version: 2.1
Name: warpspeed-googlesearch-python
Version: 1.1.0
Summary: A Python library for scraping the Google search engine. Forked from https://pypi.org/project/googlesearch-python/ to loosen requirements constraints.
Home-page: https://github.com/usewarpspeed/googlesearch
Author: Warpspeed
License: UNKNOWN
Platform: UNKNOWN
Classifier: Programming Language :: Python :: 3
Classifier: License :: OSI Approved :: MIT License
Classifier: Operating System :: OS Independent
Requires-Python: >=3.6
License-File: LICENSE
